README.md
setup.cfg
setup.py
gau_my_distributions/Binomialdistribution.py
gau_my_distributions/Gaussiandistribution.py
gau_my_distributions/Generaldistribution.py
gau_my_distributions/__init__.py
gau_my_distributions.egg-info/PKG-INFO
gau_my_distributions.egg-info/SOURCES.txt
gau_my_distributions.egg-info/dependency_links.txt
gau_my_distributions.egg-info/not-zip-safe
gau_my_distributions.egg-info/top_level.txt