Metadata-Version: 1.0
Name: gau-my-distributions
Version: 0.1
Summary: Gaussian distributions
Home-page: UNKNOWN
Author: Ananth Mamidipally
Author-email: test@testemail.com
License: UNKNOWN
Platform: UNKNOWN
